src/filter_decimation/clock_div/clock_div.v
module clock_div (
  input wire in_clk,
  input wire rst,
  output wire out_clk
);
  (* keep *) reg [7:0] counter;
  assign out_clk = ~counter[7];
  always @(posedge in_clk or negedge rst) begin
    if (!rst) begin
      counter <= 8'b0;
    end else begin
      counter <= counter + 1'b1;
    end
  end
endmodule

src/filter_decimation/clock_div/tb_clock_div.v
`timescale 1ns / 1ps

module tb_clock_div;

    // 1. Deklarasi Sinyal Testbench
    reg  in_clk;
    reg  rst;
    wire out_clk;

    // 2. Instansiasi Unit Under Test (UUT)
    clock_div uut (
        .in_clk(in_clk),
        .rst(rst),
        .out_clk(out_clk)
    );

    // 3. Generator Clock Cepat (fs = 12.288 MHz)
    // Periode penuh ≈ 81.38 ns, Setengah periode = 40.69 ns
    always begin
        #40.69 in_clk = ~in_clk;
    end

    // 4. Stimulus Skenario Pengujian
    initial begin
        // Kondisi Awal Detik Ke-0
        in_clk = 0;
        rst = 1;

        // Picu Asynchronous Reset Aktif Rendah
        #10  rst = 0; 
        #50  rst = 1; // Lepas reset
        
        // Membiarkan simulasi berjalan cukup lama agar counter melewati 256 siklus
        // Kita butuh setidaknya melihat minimal 2 pulsa output (256 * 2 * 81.38 ns ≈ 41666 ns)
        #45000;

        $display("[INFO] Simulasi pembagi clock selesai.");
        $finish;
    end

    // 5. Otomasi Pembuatan File VCD Gelombang
    initial begin
        $dumpfile("clock_div_sim.vcd");
        $dumpvars(0, tb_clock_div);
    end

endmodule

src/filter_decimation/clock_div/clock_div_sim.vcd
$date
	Sat Jun 27 23:27:20 2026
$end
$version
	Icarus Verilog
$end
$timescale
	1ps
$end
$scope module tb_clock_div $end
$var wire 1 ! out_clk $end
$var reg 1 " in_clk $end
$var reg 1 # rst $end
$scope module uut $end
$var wire 1 " in_clk $end
$var wire 1 ! out_clk $end
$var wire 1 # rst $end
$var reg 8 $ counter [7:0] $end
$upscope $end
$upscope $end
$enddefinitions $end
$comment Show the parameter values. $end
$dumpall
$end
#0
$dumpvars
bx $
1#
0"
x!
$end
#10000
1!
b0 $
0#
#40690
1"
#60000
1#
#81380
0"
#122070
b1 $
1"
#162760
0"
#203450
b10 $
1"
#244140
0"
#284830
b11 $
1"
#325520
0"
#366210
b100 $
1"
#406900
0"
#447590
b101 $
1"
#488280
0"
#528970
b110 $
1"
#569660
0"
#610350
b111 $
1"
#651040
0"
#691730
b1000 $
1"
#732420
0"
#773110
b1001 $
1"
#813800
0"
#854490
b1010 $
1"
#895180
0"
#935870
b1011 $
1"
#976560
0"
#1017250
b1100 $
1"
#1057940
0"
#1098630
b1101 $
1"
#1139320
0"
#1180010
b1110 $
1"
#1220700
0"
#1261390
b1111 $
1"
#1302080
0"
#1342770
b10000 $
1"
#1383460
0"
#1424150
b10001 $
1"
#1464840
0"
#1505530
b10010 $
1"
#1546220
0"
#1586910
b10011 $
1"
#1627600
0"
#1668290
b10100 $
1"
#1708980
0"
#1749670
b10101 $
1"
#1790360
0"
#1831050
b10110 $
1"
#1871740
0"
#1912430
b10111 $
1"
#1953120
0"
#1993810
b11000 $
1"
#2034500
0"
#2075190
b11001 $
1"
#2115880
0"
#2156570
b11010 $
1"
#2197260
0"
#2237950
b11011 $
1"
#2278640
0"
#2319330
b11100 $
1"
#2360020
0"
#2400710
b11101 $
1"
#2441400
0"
#2482090
b11110 $
1"
#2522780
0"
#2563470
b11111 $
1"
#2604160
0"
#2644850
b100000 $
1"
#2685540
0"
#2726230
b100001 $
1"
#2766920
0"
#2807610
b100010 $
1"
#2848300
0"
#2888990
b100011 $
1"
#2929680
0"
#2970370
b100100 $
1"
#3011060
0"
#3051750
b100101 $
1"
#3092440
0"
#3133130
b100110 $
1"
#3173820
0"
#3214510
b100111 $
1"
#3255200
0"
#3295890
b101000 $
1"
#3336580
0"
#3377270
b101001 $
1"
#3417960
0"
#3458650
b101010 $
1"
#3499340
0"
#3540030
b101011 $
1"
#3580720
0"
#3621410
b101100 $
1"
#3662100
0"
#3702790
b101101 $
1"
#3743480
0"
#3784170
b101110 $
1"
#3824860
0"
#3865550
b101111 $
1"
#3906240
0"
#3946930
b110000 $
1"
#3987620
0"
#4028310
b110001 $
1"
#4069000
0"
#4109690
b110010 $
1"
#4150380
0"
#4191070
b110011 $
1"
#4231760
0"
#4272450
b110100 $
1"
#4313140
0"
#4353830
b110101 $
1"
#4394520
0"
#4435210
b110110 $
1"
#4475900
0"
#4516590
b110111 $
1"
#4557280
0"
#4597970
b111000 $
1"
#4638660
0"
#4679350
b111001 $
1"
#4720040
0"
#4760730
b111010 $
1"
#4801420
0"
#4842110
b111011 $
1"
#4882800
0"
#4923490
b111100 $
1"
#4964180
0"
#5004870
b111101 $
1"
#5045560
0"
#5086250
b111110 $
1"
#5126940
0"
#5167630
b111111 $
1"
#5208320
0"
#5249010
b1000000 $
1"
#5289700
0"
#5330390
b1000001 $
1"
#5371080
0"
#5411770
b1000010 $
1"
#5452460
0"
#5493150
b1000011 $
1"
#5533840
0"
#5574530
b1000100 $
1"
#5615220
0"
#5655910
b1000101 $
1"
#5696600
0"
#5737290
b1000110 $
1"
#5777980
0"
#5818670
b1000111 $
1"
#5859360
0"
#5900050
b1001000 $
1"
#5940740
0"
#5981430
b1001001 $
1"
#6022120
0"
#6062810
b1001010 $
1"
#6103500
0"
#6144190
b1001011 $
1"
#6184880
0"
#6225570
b1001100 $
1"
#6266260
0"
#6306950
b1001101 $
1"
#6347640
0"
#6388330
b1001110 $
1"
#6429020
0"
#6469710
b1001111 $
1"
#6510400
0"
#6551090
b1010000 $
1"
#6591780
0"
#6632470
b1010001 $
1"
#6673160
0"
#6713850
b1010010 $
1"
#6754540
0"
#6795230
b1010011 $
1"
#6835920
0"
#6876610
b1010100 $
1"
#6917300
0"
#6957990
b1010101 $
1"
#6998680
0"
#7039370
b1010110 $
1"
#7080060
0"
#7120750
b1010111 $
1"
#7161440
0"
#7202130
b1011000 $
1"
#7242820
0"
#7283510
b1011001 $
1"
#7324200
0"
#7364890
b1011010 $
1"
#7405580
0"
#7446270
b1011011 $
1"
#7486960
0"
#7527650
b1011100 $
1"
#7568340
0"
#7609030
b1011101 $
1"
#7649720
0"
#7690410
b1011110 $
1"
#7731100
0"
#7771790
b1011111 $
1"
#7812480
0"
#7853170
b1100000 $
1"
#7893860
0"
#7934550
b1100001 $
1"
#7975240
0"
#8015930
b1100010 $
1"
#8056620
0"
#8097310
b1100011 $
1"
#8138000
0"
#8178690
b1100100 $
1"
#8219380
0"
#8260070
b1100101 $
1"
#8300760
0"
#8341450
b1100110 $
1"
#8382140
0"
#8422830
b1100111 $
1"
#8463520
0"
#8504210
b1101000 $
1"
#8544900
0"
#8585590
b1101001 $
1"
#8626280
0"
#8666970
b1101010 $
1"
#8707660
0"
#8748350
b1101011 $
1"
#8789040
0"
#8829730
b1101100 $
1"
#8870420
0"
#8911110
b1101101 $
1"
#8951800
0"
#8992490
b1101110 $
1"
#9033180
0"
#9073870
b1101111 $
1"
#9114560
0"
#9155250
b1110000 $
1"
#9195940
0"
#9236630
b1110001 $
1"
#9277320
0"
#9318010
b1110010 $
1"
#9358700
0"
#9399390
b1110011 $
1"
#9440080
0"
#9480770
b1110100 $
1"
#9521460
0"
#9562150
b1110101 $
1"
#9602840
0"
#9643530
b1110110 $
1"
#9684220
0"
#9724910
b1110111 $
1"
#9765600
0"
#9806290
b1111000 $
1"
#9846980
0"
#9887670
b1111001 $
1"
#9928360
0"
#9969050
b1111010 $
1"
#10009740
0"
#10050430
b1111011 $
1"
#10091120
0"
#10131810
b1111100 $
1"
#10172500
0"
#10213190
b1111101 $
1"
#10253880
0"
#10294570
b1111110 $
1"
#10335260
0"
#10375950
b1111111 $
1"
#10416640
0"
#10457330
0!
b10000000 $
1"
#10498020
0"
#10538710
b10000001 $
1"
#10579400
0"
#10620090
b10000010 $
1"
#10660780
0"
#10701470
b10000011 $
1"
#10742160
0"
#10782850
b10000100 $
1"
#10823540
0"
#10864230
b10000101 $
1"
#10904920
0"
#10945610
b10000110 $
1"
#10986300
0"
#11026990
b10000111 $
1"
#11067680
0"
#11108370
b10001000 $
1"
#11149060
0"
#11189750
b10001001 $
1"
#11230440
0"
#11271130
b10001010 $
1"
#11311820
0"
#11352510
b10001011 $
1"
#11393200
0"
#11433890
b10001100 $
1"
#11474580
0"
#11515270
b10001101 $
1"
#11555960
0"
#11596650
b10001110 $
1"
#11637340
0"
#11678030
b10001111 $
1"
#11718720
0"
#11759410
b10010000 $
1"
#11800100
0"
#11840790
b10010001 $
1"
#11881480
0"
#11922170
b10010010 $
1"
#11962860
0"
#12003550
b10010011 $
1"
#12044240
0"
#12084930
b10010100 $
1"
#12125620
0"
#12166310
b10010101 $
1"
#12207000
0"
#12247690
b10010110 $
1"
#12288380
0"
#12329070
b10010111 $
1"
#12369760
0"
#12410450
b10011000 $
1"
#12451140
0"
#12491830
b10011001 $
1"
#12532520
0"
#12573210
b10011010 $
1"
#12613900
0"
#12654590
b10011011 $
1"
#12695280
0"
#12735970
b10011100 $
1"
#12776660
0"
#12817350
b10011101 $
1"
#12858040
0"
#12898730
b10011110 $
1"
#12939420
0"
#12980110
b10011111 $
1"
#13020800
0"
#13061490
b10100000 $
1"
#13102180
0"
#13142870
b10100001 $
1"
#13183560
0"
#13224250
b10100010 $
1"
#13264940
0"
#13305630
b10100011 $
1"
#13346320
0"
#13387010
b10100100 $
1"
#13427700
0"
#13468390
b10100101 $
1"
#13509080
0"
#13549770
b10100110 $
1"
#13590460
0"
#13631150
b10100111 $
1"
#13671840
0"
#13712530
b10101000 $
1"
#13753220
0"
#13793910
b10101001 $
1"
#13834600
0"
#13875290
b10101010 $
1"
#13915980
0"
#13956670
b10101011 $
1"
#13997360
0"
#14038050
b10101100 $
1"
#14078740
0"
#14119430
b10101101 $
1"
#14160120
0"
#14200810
b10101110 $
1"
#14241500
0"
#14282190
b10101111 $
1"
#14322880
0"
#14363570
b10110000 $
1"
#14404260
0"
#14444950
b10110001 $
1"
#14485640
0"
#14526330
b10110010 $
1"
#14567020
0"
#14607710
b10110011 $
1"
#14648400
0"
#14689090
b10110100 $
1"
#14729780
0"
#14770470
b10110101 $
1"
#14811160
0"
#14851850
b10110110 $
1"
#14892540
0"
#14933230
b10110111 $
1"
#14973920
0"
#15014610
b10111000 $
1"
#15055300
0"
#15095990
b10111001 $
1"
#15136680
0"
#15177370
b10111010 $
1"
#15218060
0"
#15258750
b10111011 $
1"
#15299440
0"
#15340130
b10111100 $
1"
#15380820
0"
#15421510
b10111101 $
1"
#15462200
0"
#15502890
b10111110 $
1"
#15543580
0"
#15584270
b10111111 $
1"
#15624960
0"
#15665650
b11000000 $
1"
#15706340
0"
#15747030
b11000001 $
1"
#15787720
0"
#15828410
b11000010 $
1"
#15869100
0"
#15909790
b11000011 $
1"
#15950480
0"
#15991170
b11000100 $
1"
#16031860
0"
#16072550
b11000101 $
1"
#16113240
0"
#16153930
b11000110 $
1"
#16194620
0"
#16235310
b11000111 $
1"
#16276000
0"
#16316690
b11001000 $
1"
#16357380
0"
#16398070
b11001001 $
1"
#16438760
0"
#16479450
b11001010 $
1"
#16520140
0"
#16560830
b11001011 $
1"
#16601520
0"
#16642210
b11001100 $
1"
#16682900
0"
#16723590
b11001101 $
1"
#16764280
0"
#16804970
b11001110 $
1"
#16845660
0"
#16886350
b11001111 $
1"
#16927040
0"
#16967730
b11010000 $
1"
#17008420
0"
#17049110
b11010001 $
1"
#17089800
0"
#17130490
b11010010 $
1"
#17171180
0"
#17211870
b11010011 $
1"
#17252560
0"
#17293250
b11010100 $
1"
#17333940
0"
#17374630
b11010101 $
1"
#17415320
0"
#17456010
b11010110 $
1"
#17496700
0"
#17537390
b11010111 $
1"
#17578080
0"
#17618770
b11011000 $
1"
#17659460
0"
#17700150
b11011001 $
1"
#17740840
0"
#17781530
b11011010 $
1"
#17822220
0"
#17862910
b11011011 $
1"
#17903600
0"
#17944290
b11011100 $
1"
#17984980
0"
#18025670
b11011101 $
1"
#18066360
0"
#18107050
b11011110 $
1"
#18147740
0"
#18188430
b11011111 $
1"
#18229120
0"
#18269810
b11100000 $
1"
#18310500
0"
#18351190
b11100001 $
1"
#18391880
0"
#18432570
b11100010 $
1"
#18473260
0"
#18513950
b11100011 $
1"
#18554640
0"
#18595330
b11100100 $
1"
#18636020
0"
#18676710
b11100101 $
1"
#18717400
0"
#18758090
b11100110 $
1"
#18798780
0"
#18839470
b11100111 $
1"
#18880160
0"
#18920850
b11101000 $
1"
#18961540
0"
#19002230
b11101001 $
1"
#19042920
0"
#19083610
b11101010 $
1"
#19124300
0"
#19164990
b11101011 $
1"
#19205680
0"
#19246370
b11101100 $
1"
#19287060
0"
#19327750
b11101101 $
1"
#19368440
0"
#19409130
b11101110 $
1"
#19449820
0"
#19490510
b11101111 $
1"
#19531200
0"
#19571890
b11110000 $
1"
#19612580
0"
#19653270
b11110001 $
1"
#19693960
0"
#19734650
b11110010 $
1"
#19775340
0"
#19816030
b11110011 $
1"
#19856720
0"
#19897410
b11110100 $
1"
#19938100
0"
#19978790
b11110101 $
1"
#20019480
0"
#20060170
b11110110 $
1"
#20100860
0"
#20141550
b11110111 $
1"
#20182240
0"
#20222930
b11111000 $
1"
#20263620
0"
#20304310
b11111001 $
1"
#20345000
0"
#20385690
b11111010 $
1"
#20426380
0"
#20467070
b11111011 $
1"
#20507760
0"
#20548450
b11111100 $
1"
#20589140
0"
#20629830
b11111101 $
1"
#20670520
0"
#20711210
b11111110 $
1"
#20751900
0"
#20792590
b11111111 $
1"
#20833280
0"
#20873970
1!
b0 $
1"
#20914660
0"
#20955350
b1 $
1"
#20996040
0"
#21036730
b10 $
1"
#21077420
0"
#21118110
b11 $
1"
#21158800
0"
#21199490
b100 $
1"
#21240180
0"
#21280870
b101 $
1"
#21321560
0"
#21362250
b110 $
1"
#21402940
0"
#21443630
b111 $
1"
#21484320
0"
#21525010
b1000 $
1"
#21565700
0"
#21606390
b1001 $
1"
#21647080
0"
#21687770
b1010 $
1"
#21728460
0"
#21769150
b1011 $
1"
#21809840
0"
#21850530
b1100 $
1"
#21891220
0"
#21931910
b1101 $
1"
#21972600
0"
#22013290
b1110 $
1"
#22053980
0"
#22094670
b1111 $
1"
#22135360
0"
#22176050
b10000 $
1"
#22216740
0"
#22257430
b10001 $
1"
#22298120
0"
#22338810
b10010 $
1"
#22379500
0"
#22420190
b10011 $
1"
#22460880
0"
#22501570
b10100 $
1"
#22542260
0"
#22582950
b10101 $
1"
#22623640
0"
#22664330
b10110 $
1"
#22705020
0"
#22745710
b10111 $
1"
#22786400
0"
#22827090
b11000 $
1"
#22867780
0"
#22908470
b11001 $
1"
#22949160
0"
#22989850
b11010 $
1"
#23030540
0"
#23071230
b11011 $
1"
#23111920
0"
#23152610
b11100 $
1"
#23193300
0"
#23233990
b11101 $
1"
#23274680
0"
#23315370
b11110 $
1"
#23356060
0"
#23396750
b11111 $
1"
#23437440
0"
#23478130
b100000 $
1"
#23518820
0"
#23559510
b100001 $
1"
#23600200
0"
#23640890
b100010 $
1"
#23681580
0"
#23722270
b100011 $
1"
#23762960
0"
#23803650
b100100 $
1"
#23844340
0"
#23885030
b100101 $
1"
#23925720
0"
#23966410
b100110 $
1"
#24007100
0"
#24047790
b100111 $
1"
#24088480
0"
#24129170
b101000 $
1"
#24169860
0"
#24210550
b101001 $
1"
#24251240
0"
#24291930
b101010 $
1"
#24332620
0"
#24373310
b101011 $
1"
#24414000
0"
#24454690
b101100 $
1"
#24495380
0"
#24536070
b101101 $
1"
#24576760
0"
#24617450
b101110 $
1"
#24658140
0"
#24698830
b101111 $
1"
#24739520
0"
#24780210
b110000 $
1"
#24820900
0"
#24861590
b110001 $
1"
#24902280
0"
#24942970
b110010 $
1"
#24983660
0"
#25024350
b110011 $
1"
#25065040
0"
#25105730
b110100 $
1"
#25146420
0"
#25187110
b110101 $
1"
#25227800
0"
#25268490
b110110 $
1"
#25309180
0"
#25349870
b110111 $
1"
#25390560
0"
#25431250
b111000 $
1"
#25471940
0"
#25512630
b111001 $
1"
#25553320
0"
#25594010
b111010 $
1"
#25634700
0"
#25675390
b111011 $
1"
#25716080
0"
#25756770
b111100 $
1"
#25797460
0"
#25838150
b111101 $
1"
#25878840
0"
#25919530
b111110 $
1"
#25960220
0"
#26000910
b111111 $
1"
#26041600
0"
#26082290
b1000000 $
1"
#26122980
0"
#26163670
b1000001 $
1"
#26204360
0"
#26245050
b1000010 $
1"
#26285740
0"
#26326430
b1000011 $
1"
#26367120
0"
#26407810
b1000100 $
1"
#26448500
0"
#26489190
b1000101 $
1"
#26529880
0"
#26570570
b1000110 $
1"
#26611260
0"
#26651950
b1000111 $
1"
#26692640
0"
#26733330
b1001000 $
1"
#26774020
0"
#26814710
b1001001 $
1"
#26855400
0"
#26896090
b1001010 $
1"
#26936780
0"
#26977470
b1001011 $
1"
#27018160
0"
#27058850
b1001100 $
1"
#27099540
0"
#27140230
b1001101 $
1"
#27180920
0"
#27221610
b1001110 $
1"
#27262300
0"
#27302990
b1001111 $
1"
#27343680
0"
#27384370
b1010000 $
1"
#27425060
0"
#27465750
b1010001 $
1"
#27506440
0"
#27547130
b1010010 $
1"
#27587820
0"
#27628510
b1010011 $
1"
#27669200
0"
#27709890
b1010100 $
1"
#27750580
0"
#27791270
b1010101 $
1"
#27831960
0"
#27872650
b1010110 $
1"
#27913340
0"
#27954030
b1010111 $
1"
#27994720
0"
#28035410
b1011000 $
1"
#28076100
0"
#28116790
b1011001 $
1"
#28157480
0"
#28198170
b1011010 $
1"
#28238860
0"
#28279550
b1011011 $
1"
#28320240
0"
#28360930
b1011100 $
1"
#28401620
0"
#28442310
b1011101 $
1"
#28483000
0"
#28523690
b1011110 $
1"
#28564380
0"
#28605070
b1011111 $
1"
#28645760
0"
#28686450
b1100000 $
1"
#28727140
0"
#28767830
b1100001 $
1"
#28808520
0"
#28849210
b1100010 $
1"
#28889900
0"
#28930590
b1100011 $
1"
#28971280
0"
#29011970
b1100100 $
1"
#29052660
0"
#29093350
b1100101 $
1"
#29134040
0"
#29174730
b1100110 $
1"
#29215420
0"
#29256110
b1100111 $
1"
#29296800
0"
#29337490
b1101000 $
1"
#29378180
0"
#29418870
b1101001 $
1"
#29459560
0"
#29500250
b1101010 $
1"
#29540940
0"
#29581630
b1101011 $
1"
#29622320
0"
#29663010
b1101100 $
1"
#29703700
0"
#29744390
b1101101 $
1"
#29785080
0"
#29825770
b1101110 $
1"
#29866460
0"
#29907150
b1101111 $
1"
#29947840
0"
#29988530
b1110000 $
1"
#30029220
0"
#30069910
b1110001 $
1"
#30110600
0"
#30151290
b1110010 $
1"
#30191980
0"
#30232670
b1110011 $
1"
#30273360
0"
#30314050
b1110100 $
1"
#30354740
0"
#30395430
b1110101 $
1"
#30436120
0"
#30476810
b1110110 $
1"
#30517500
0"
#30558190
b1110111 $
1"
#30598880
0"
#30639570
b1111000 $
1"
#30680260
0"
#30720950
b1111001 $
1"
#30761640
0"
#30802330
b1111010 $
1"
#30843020
0"
#30883710
b1111011 $
1"
#30924400
0"
#30965090
b1111100 $
1"
#31005780
0"
#31046470
b1111101 $
1"
#31087160
0"
#31127850
b1111110 $
1"
#31168540
0"
#31209230
b1111111 $
1"
#31249920
0"
#31290610
0!
b10000000 $
1"
#31331300
0"
#31371990
b10000001 $
1"
#31412680
0"
#31453370
b10000010 $
1"
#31494060
0"
#31534750
b10000011 $
1"
#31575440
0"
#31616130
b10000100 $
1"
#31656820
0"
#31697510
b10000101 $
1"
#31738200
0"
#31778890
b10000110 $
1"
#31819580
0"
#31860270
b10000111 $
1"
#31900960
0"
#31941650
b10001000 $
1"
#31982340
0"
#32023030
b10001001 $
1"
#32063720
0"
#32104410
b10001010 $
1"
#32145100
0"
#32185790
b10001011 $
1"
#32226480
0"
#32267170
b10001100 $
1"
#32307860
0"
#32348550
b10001101 $
1"
#32389240
0"
#32429930
b10001110 $
1"
#32470620
0"
#32511310
b10001111 $
1"
#32552000
0"
#32592690
b10010000 $
1"
#32633380
0"
#32674070
b10010001 $
1"
#32714760
0"
#32755450
b10010010 $
1"
#32796140
0"
#32836830
b10010011 $
1"
#32877520
0"
#32918210
b10010100 $
1"
#32958900
0"
#32999590
b10010101 $
1"
#33040280
0"
#33080970
b10010110 $
1"
#33121660
0"
#33162350
b10010111 $
1"
#33203040
0"
#33243730
b10011000 $
1"
#33284420
0"
#33325110
b10011001 $
1"
#33365800
0"
#33406490
b10011010 $
1"
#33447180
0"
#33487870
b10011011 $
1"
#33528560
0"
#33569250
b10011100 $
1"
#33609940
0"
#33650630
b10011101 $
1"
#33691320
0"
#33732010
b10011110 $
1"
#33772700
0"
#33813390
b10011111 $
1"
#33854080
0"
#33894770
b10100000 $
1"
#33935460
0"
#33976150
b10100001 $
1"
#34016840
0"
#34057530
b10100010 $
1"
#34098220
0"
#34138910
b10100011 $
1"
#34179600
0"
#34220290
b10100100 $
1"
#34260980
0"
#34301670
b10100101 $
1"
#34342360
0"
#34383050
b10100110 $
1"
#34423740
0"
#34464430
b10100111 $
1"
#34505120
0"
#34545810
b10101000 $
1"
#34586500
0"
#34627190
b10101001 $
1"
#34667880
0"
#34708570
b10101010 $
1"
#34749260
0"
#34789950
b10101011 $
1"
#34830640
0"
#34871330
b10101100 $
1"
#34912020
0"
#34952710
b10101101 $
1"
#34993400
0"
#35034090
b10101110 $
1"
#35074780
0"
#35115470
b10101111 $
1"
#35156160
0"
#35196850
b10110000 $
1"
#35237540
0"
#35278230
b10110001 $
1"
#35318920
0"
#35359610
b10110010 $
1"
#35400300
0"
#35440990
b10110011 $
1"
#35481680
0"
#35522370
b10110100 $
1"
#35563060
0"
#35603750
b10110101 $
1"
#35644440
0"
#35685130
b10110110 $
1"
#35725820
0"
#35766510
b10110111 $
1"
#35807200
0"
#35847890
b10111000 $
1"
#35888580
0"
#35929270
b10111001 $
1"
#35969960
0"
#36010650
b10111010 $
1"
#36051340
0"
#36092030
b10111011 $
1"
#36132720
0"
#36173410
b10111100 $
1"
#36214100
0"
#36254790
b10111101 $
1"
#36295480
0"
#36336170
b10111110 $
1"
#36376860
0"
#36417550
b10111111 $
1"
#36458240
0"
#36498930
b11000000 $
1"
#36539620
0"
#36580310
b11000001 $
1"
#36621000
0"
#36661690
b11000010 $
1"
#36702380
0"
#36743070
b11000011 $
1"
#36783760
0"
#36824450
b11000100 $
1"
#36865140
0"
#36905830
b11000101 $
1"
#36946520
0"
#36987210
b11000110 $
1"
#37027900
0"
#37068590
b11000111 $
1"
#37109280
0"
#37149970
b11001000 $
1"
#37190660
0"
#37231350
b11001001 $
1"
#37272040
0"
#37312730
b11001010 $
1"
#37353420
0"
#37394110
b11001011 $
1"
#37434800
0"
#37475490
b11001100 $
1"
#37516180
0"
#37556870
b11001101 $
1"
#37597560
0"
#37638250
b11001110 $
1"
#37678940
0"
#37719630
b11001111 $
1"
#37760320
0"
#37801010
b11010000 $
1"
#37841700
0"
#37882390
b11010001 $
1"
#37923080
0"
#37963770
b11010010 $
1"
#38004460
0"
#38045150
b11010011 $
1"
#38085840
0"
#38126530
b11010100 $
1"
#38167220
0"
#38207910
b11010101 $
1"
#38248600
0"
#38289290
b11010110 $
1"
#38329980
0"
#38370670
b11010111 $
1"
#38411360
0"
#38452050
b11011000 $
1"
#38492740
0"
#38533430
b11011001 $
1"
#38574120
0"
#38614810
b11011010 $
1"
#38655500
0"
#38696190
b11011011 $
1"
#38736880
0"
#38777570
b11011100 $
1"
#38818260
0"
#38858950
b11011101 $
1"
#38899640
0"
#38940330
b11011110 $
1"
#38981020
0"
#39021710
b11011111 $
1"
#39062400
0"
#39103090
b11100000 $
1"
#39143780
0"
#39184470
b11100001 $
1"
#39225160
0"
#39265850
b11100010 $
1"
#39306540
0"
#39347230
b11100011 $
1"
#39387920
0"
#39428610
b11100100 $
1"
#39469300
0"
#39509990
b11100101 $
1"
#39550680
0"
#39591370
b11100110 $
1"
#39632060
0"
#39672750
b11100111 $
1"
#39713440
0"
#39754130
b11101000 $
1"
#39794820
0"
#39835510
b11101001 $
1"
#39876200
0"
#39916890
b11101010 $
1"
#39957580
0"
#39998270
b11101011 $
1"
#40038960
0"
#40079650
b11101100 $
1"
#40120340
0"
#40161030
b11101101 $
1"
#40201720
0"
#40242410
b11101110 $
1"
#40283100
0"
#40323790
b11101111 $
1"
#40364480
0"
#40405170
b11110000 $
1"
#40445860
0"
#40486550
b11110001 $
1"
#40527240
0"
#40567930
b11110010 $
1"
#40608620
0"
#40649310
b11110011 $
1"
#40690000
0"
#40730690
b11110100 $
1"
#40771380
0"
#40812070
b11110101 $
1"
#40852760
0"
#40893450
b11110110 $
1"
#40934140
0"
#40974830
b11110111 $
1"
#41015520
0"
#41056210
b11111000 $
1"
#41096900
0"
#41137590
b11111001 $
1"
#41178280
0"
#41218970
b11111010 $
1"
#41259660
0"
#41300350
b11111011 $
1"
#41341040
0"
#41381730
b11111100 $
1"
#41422420
0"
#41463110
b11111101 $
1"
#41503800
0"
#41544490
b11111110 $
1"
#41585180
0"
#41625870
b11111111 $
1"
#41666560
0"
#41707250
1!
b0 $
1"
#41747940
0"
#41788630
b1 $
1"
#41829320
0"
#41870010
b10 $
1"
#41910700
0"
#41951390
b11 $
1"
#41992080
0"
#42032770
b100 $
1"
#42073460
0"
#42114150
b101 $
1"
#42154840
0"
#42195530
b110 $
1"
#42236220
0"
#42276910
b111 $
1"
#42317600
0"
#42358290
b1000 $
1"
#42398980
0"
#42439670
b1001 $
1"
#42480360
0"
#42521050
b1010 $
1"
#42561740
0"
#42602430
b1011 $
1"
#42643120
0"
#42683810
b1100 $
1"
#42724500
0"
#42765190
b1101 $
1"
#42805880
0"
#42846570
b1110 $
1"
#42887260
0"
#42927950
b1111 $
1"
#42968640
0"
#43009330
b10000 $
1"
#43050020
0"
#43090710
b10001 $
1"
#43131400
0"
#43172090
b10010 $
1"
#43212780
0"
#43253470
b10011 $
1"
#43294160
0"
#43334850
b10100 $
1"
#43375540
0"
#43416230
b10101 $
1"
#43456920
0"
#43497610
b10110 $
1"
#43538300
0"
#43578990
b10111 $
1"
#43619680
0"
#43660370
b11000 $
1"
#43701060
0"
#43741750
b11001 $
1"
#43782440
0"
#43823130
b11010 $
1"
#43863820
0"
#43904510
b11011 $
1"
#43945200
0"
#43985890
b11100 $
1"
#44026580
0"
#44067270
b11101 $
1"
#44107960
0"
#44148650
b11110 $
1"
#44189340
0"
#44230030
b11111 $
1"
#44270720
0"
#44311410
b100000 $
1"
#44352100
0"
#44392790
b100001 $
1"
#44433480
0"
#44474170
b100010 $
1"
#44514860
0"
#44555550
b100011 $
1"
#44596240
0"
#44636930
b100100 $
1"
#44677620
0"
#44718310
b100101 $
1"
#44759000
0"
#44799690
b100110 $
1"
#44840380
0"
#44881070
b100111 $
1"
#44921760
0"
#44962450
b101000 $
1"
#45003140
0"
#45043830
b101001 $
1"
