src/filter_decimation/cic_filter/integrator.v
module integrator (
  input wire [24:0] in_int,
  input wire        rst,
  input wire        clk,
  output reg [24:0] out_int
);
  always @(posedge clk or negedge rst) begin
    if (!rst) begin
      out_int <= 25'b0;
    end else begin
      out_int <= out_int + in_int;
    end
  end
endmodule

src/filter_decimation/integrator/tb_integrator.v
`timescale 1ns / 1ps

module tb_integrator;

    // 1. Deklarasi Sinyal Testbench
    reg [24:0] in_int;
    reg        rst;
    reg        clk;
    wire [24:0] out_int;

    // 2. Instansiasi Unit Under Test (UUT)
    integrator uut (
        .in_int(in_int),
        .rst(rst),
        .clk(clk),
        .out_int(out_int)
    );

    // 3. Generator Clock Acuan (fs = 12.288 MHz)
    // Periode Clock = 1 / 12.288 MHz ≈ 81.38 ns. 
    // Maka satukan nilai half-period menjadi 40.69 ns.
    always begin
        #40.69 clk = ~clk;
    end

    // 4. Skenario Pengujian Sinyal (Stimulus)
    initial begin
        // Kondisi Awal
        clk = 0;
        rst = 1;
        in_int = 25'b0;

        // Pemicuan Asynchronous Reset (Aktif Rendah)
        #10 rst = 0; // Aktifkan reset
        #50 rst = 1; // Lepas reset setelah 50ns
        
        // Menunggu sinkronisasi beberapa saat setelah reset selesai
        @(posedge clk);
        
        // --- Skenario 1: Memasukkan angka 1 terus-menerus ---
        // Kita ingin melihat out_int naik perlahan: 0 -> 1 -> 2 -> 3 -> 4...
        $display("[INFO] Memulai Skenario 1: Akumulasi Konstan (+1)");
        in_int = 25'd1; 
        repeat(5) @(posedge clk); // Biarkan berjalan selama 5 siklus clock

        // --- Skenario 2: Memasukkan nilai yang lebih besar ---
        // Kita ingin melihat lompatan nilai akumulasi yang drastis
        $display("[INFO] Memulai Skenario 2: Akumulasi Nilai Besar (+500)");
        in_int = 25'd500;
        repeat(4) @(posedge clk);

        // --- Skenario 3: Memasukkan nilai 0 ---
        // Nilai out_int seharusnya bertahan tetap di posisi terakhir (tidak naik/turun)
        $display("[INFO] Memulai Skenario 3: Menahan Nilai Terakhir (+0)");
        in_int = 25'd0;
        repeat(3) @(posedge clk);

        // Selesai simulasi
        $display("[INFO] Simulasi selesai dengan sukses.");
        $finish;
    end

    // 5. Blok Otomatisasi untuk menghasilkan file VCD (Bisa dibuka di GTKWave)
    initial begin
        $dumpfile("integrator_sim.vcd"); // Nama file output gelombang
        $dumpvars(0, tb_integrator);    // Merekam seluruh tingkat hierarki sirkuit
    end

endmodule

src/filter_decimation/integrator/integrator_sim.vcd
$date
	Sat Jun 27 20:38:52 2026
$end
$version
	Icarus Verilog
$end
$timescale
	1ps
$end
$scope module tb_integrator $end
$var wire 25 ! out_int [24:0] $end
$var reg 1 " clk $end
$var reg 25 # in_int [24:0] $end
$var reg 1 $ rst $end
$scope module uut $end
$var wire 1 " clk $end
$var wire 25 % in_int [24:0] $end
$var wire 1 $ rst $end
$var reg 25 & out_int [24:0] $end
$upscope $end
$upscope $end
$enddefinitions $end
$comment Show the parameter values. $end
$dumpall
$end
#0
$dumpvars
bx &
b0 %
1$
b0 #
0"
bx !
$end
#10000
b0 !
b0 &
0$
#40690
1"
#60000
1$
#81380
0"
#122070
b1 !
b1 &
b1 #
b1 %
1"
#162760
0"
#203450
b10 !
b10 &
1"
#244140
0"
#284830
b11 !
b11 &
1"
#325520
0"
#366210
b100 !
b100 &
1"
#406900
0"
#447590
b101 !
b101 &
1"
#488280
0"
#528970
b111111001 !
b111111001 &
b111110100 #
b111110100 %
1"
#569660
0"
#610350
b1111101101 !
b1111101101 &
1"
#651040
0"
#691730
b10111100001 !
b10111100001 &
1"
#732420
0"
#773110
b11111010101 !
b11111010101 &
1"
#813800
0"
#854490
b0 #
b0 %
1"
