src/filter_decimation/cascade_diff/differentiator.v
module differentiator (
  input wire [24:0] in_diff,
  input wire        rst,
  input wire        clk,
  output reg [24:0] out_diff
);
  reg [24:0] in_min1;
  always @(posedge clk or negedge rst) begin
    if (!rst) begin
      in_min1 <= 25'b0;
      out_diff <= 25'b0;
    end else begin
      in_min1 <= in_diff;
      out_diff <= in_diff - in_min1;
    end
  end
endmodule

src/filter_decimation/differentiator/tb_differentiator.v
`timescale 1ns / 1ps

module tb_differentiator;

    // 1. Deklarasi Sinyal Testbench
    reg [24:0] in_diff;
    reg        rst;
    reg        clk;
    wire [24:0] out_diff;

    // 2. Instansiasi Unit Under Test (UUT)
    differentiator uut (
        .in_diff(in_diff),
        .rst(rst),
        .clk(clk),
        .out_diff(out_diff)
    );

    // 3. Generator Clock Lambat (f_N = 48 kHz untuk Audio Nyquist Data Rate)
    // Periode Clock = 1 / 48 kHz ≈ 20833.33 ns.
    // Setengah Periode (Half-period) = 10416.66 ns.
    always begin
        #10416.66 clk = ~clk;
    end

    // 4. Skenario Pengujian Sinyal (Stimulus)
    initial begin
        // Kondisi Awal Detik Ke-0
        clk = 0;
        rst = 1;
        in_diff = 25'b0;

        // Pemicuan Asynchronous Reset (Aktif Rendah)
        #1000 rst = 0; // Aktifkan reset
        #5000 rst = 1; // Lepas reset
        
        // Menunggu tepi clock naik agar sinkron
        @(posedge clk);
        
        // --- Skenario 1: Input Konstan (in_diff = 100) ---
        // Karena input konstan, selisihnya harusnya kembali menjadi 0 setelah clock berikutnya
        $display("[INFO] Skenario 1: Memasukkan nilai konstan 100");
        in_diff = 25'd100; // Clock ini: out_diff = 100 - 0 = 100
        @(posedge clk);   
        
        in_diff = 25'd100; // Clock berikutnya: out_diff = 100 - 100 = 0
        repeat(2) @(posedge clk);

        // --- Skenario 2: Input Naik Berundak (Ramp Input) ---
        // Kita ingin melihat out_diff mencatat nilai lompatannya
        $display("[INFO] Skenario 2: Menaikkan nilai berundak");
        in_diff = 25'd150; // out_diff = 150 - 100 = 50
        @(posedge clk);
        
        in_diff = 25'd220; // out_diff = 220 - 150 = 70
        @(posedge clk);
        
        in_diff = 25'd200; // out_diff = 200 - 220 = -20 (Komplemen Dua)
        @(posedge clk);

        // --- Skenario 3: Input Kembali Konstan ---
        in_diff = 25'd200; // out_diff = 200 - 200 = 0
        repeat(2) @(posedge clk);

        // Selesai simulasi
        $display("[INFO] Simulasi differentiator selesai.");
        $finish;
    end

    // 5. Otomasi Dumping Gelombang VCD
    initial begin
        $dumpfile("differentiator_sim.vcd");
        $dumpvars(0, tb_differentiator);
    end

endmodule

src/filter_decimation/differentiator/differentiator_sim.vcd
$date
	Sat Jun 27 23:12:04 2026
$end
$version
	Icarus Verilog
$end
$timescale
	1ps
$end
$scope module tb_differentiator $end
$var wire 25 ! out_diff [24:0] $end
$var reg 1 " clk $end
$var reg 25 # in_diff [24:0] $end
$var reg 1 $ rst $end
$scope module uut $end
$var wire 1 " clk $end
$var wire 25 % in_diff [24:0] $end
$var wire 1 $ rst $end
$var reg 25 & in_min1 [24:0] $end
$var reg 25 ' out_diff [24:0] $end
$upscope $end
$upscope $end
$enddefinitions $end
$comment Show the parameter values. $end
$dumpall
$end
#0
$dumpvars
bx '
bx &
b0 %
1$
b0 #
0"
bx !
$end
#1000000
b0 !
b0 '
b0 &
0$
#6000000
1$
#10416660
b1100100 !
b1100100 '
b1100100 &
b1100100 #
b1100100 %
1"
#20833320
0"
#31249980
b0 !
b0 '
1"
#41666640
0"
#52083300
1"
#62499960
0"
#72916620
b110010 !
b110010 '
b10010110 &
b10010110 #
b10010110 %
1"
#83333280
0"
#93749940
b1000110 !
b1000110 '
b11011100 &
b11011100 #
b11011100 %
1"
#104166600
0"
#114583260
b1111111111111111111101100 !
b1111111111111111111101100 '
b11001000 &
b11001000 #
b11001000 %
1"
#124999920
0"
#135416580
b0 !
b0 '
1"
